XME/MPI.py
XME/__init__.py
XME/Manager/Monitor.py
XME/Manager/Object.py
XME/Manager/Security.py
XME/Manager/__init__.py
XME/XMElib/ArrayOperator.py
XME/XMElib/Executor.py
XME/XMElib/Logputter.py
XME/XMElib/Monitor.py
XME/XMElib/Security.py
XME/XMElib/__init__.py
XME/XMElib/version_info.py
XME-4.2.5.dist-info/LICENSE.txt
XME-4.2.5.dist-info/METADATA
XME-4.2.5.dist-info/WHEEL
XME-4.2.5.dist-info/top_level.txt
XME-4.2.5.dist-info/RECORD
