Metadata-Version: 2.1
Name: XME
Version: 4.2.5
Summary: This is a Python interface for process pool establishment, and result collection based on the Multiprocessing module.
Home-page: https://github.com/wacmkxiaoyi/Xenon-Multiprocessing-Engine
Author: Junxiang Huang & Weihui Li
Author-email: huangjunxiang@mail.ynu.edu.cn
Classifier: Programming Language :: Python :: 3
Classifier: License :: OSI Approved :: MIT License
Classifier: Operating System :: OS Independent
Requires-Python: >=3.6
License-File: LICENSE.txt
